README
setup.py
bin/jojo
jojo/__init__.py
jojo/core.jo
jojo/jojo.py
jojo.egg-info/PKG-INFO
jojo.egg-info/SOURCES.txt
jojo.egg-info/dependency_links.txt
jojo.egg-info/top_level.txt