Metadata-Version: 1.2
Name: jojo
Version: 0.0.23
Summary: jojo's programming adventure in python
Home-page: http://github.com/xieyuheng/jojo-on-python
Author: xieyuheng
Author-email: xyheme@gmail.com
License: I dedicate all my works here to all human beings.
Platform: UNKNOWN
Requires-Python: >=3
